graphilp/__init__.py
graphilp/covering/__init__.py
graphilp/covering/k_cover.py
graphilp/covering/knapsack.py
graphilp/covering/min_dom_set.py
graphilp/covering/min_edge_dom.py
graphilp/covering/min_vertexcover.py
graphilp/covering/set_cover.py
graphilp/covering/heuristics/__init__.py
graphilp/covering/heuristics/setcover_greedy.py
graphilp/covering/heuristics/vertexcover_lp_rounding.py
graphilp/covering/heuristics/vertexcover_maximal_matching.py
graphilp/cuts_flows/__init__.py
graphilp/cuts_flows/bisection.py
graphilp/cuts_flows/max_cut.py
graphilp/cuts_flows/min_k_flow.py
graphilp/cuts_flows/min_uncut.py
graphilp/cuts_flows/heuristics/__init__.py
graphilp/cuts_flows/heuristics/maxcut_greedy.py
graphilp/imports/__init__.py
graphilp/imports/graph_formats.py
graphilp/imports/ilpgraph.py
graphilp/imports/ilpsetsystem.py
graphilp/imports/networkx.py
graphilp/matching/__init__.py
graphilp/matching/maxweight.py
graphilp/matching/perfect.py
graphilp/matching/perfect_bipartite.py
graphilp/network/__init__.py
graphilp/network/atsp.py
graphilp/network/atsp_desrochers_laporte.py
graphilp/network/gen_path_atsp.py
graphilp/network/path_atsp.py
graphilp/network/path_tsp.py
graphilp/network/pcst.py
graphilp/network/pcst_linear.py
graphilp/network/steiner.py
graphilp/network/steiner_linear.py
graphilp/network/steiner_linear_tightened.py
graphilp/network/tsp.py
graphilp/network/tsp_callbacks.py
graphilp/network/heuristics/__init__.py
graphilp/network/heuristics/steiner_metric_closure.py
graphilp/network/heuristics/tsp_christofides.py
graphilp/network/heuristics/tsp_nearest_neighbour.py
graphilp/network/heuristics/tsp_two_opt.py
graphilp/packing/__init__.py
graphilp/packing/clique_packing.py
graphilp/packing/max_indset.py
graphilp/packing/set_packing.py
graphilp/packing/heuristics/__init__.py
graphilp/packing/heuristics/setpacking_greedy.py
graphilp/partitioning/__init__.py
graphilp/partitioning/min_vertex_coloring.py
graphilp/partitioning/heuristics/__init__.py
graphilp-0.1.0.dist-info/LICENSE.txt
graphilp-0.1.0.dist-info/METADATA
graphilp-0.1.0.dist-info/WHEEL
graphilp-0.1.0.dist-info/top_level.txt
graphilp-0.1.0.dist-info/RECORD
