Metadata-Version: 2.1
Name: graphilp
Version: 0.1.0
Summary: A Python API to automatically cast graph-related optimisation problems into ILP instances for Gurobi
Home-page: https://github.com/VF-DE-CDS/GraphILP-API
Author: GraphILP API Developers
Author-email: rolf.bardeli1@vodafone.com
License: UNKNOWN
Project-URL: Bug Tracker, https://github.com/VF-DE-CDS/GraphILP-API/Issues
Project-URL: Documentation, https://vf-de-cds.github.io/GraphILP-API-docs/
Platform: UNKNOWN
Classifier: Programming Language :: Python :: 3
Classifier: License :: OSI Approved :: MIT License
Classifier: Operating System :: OS Independent
Requires-Python: >=3.5
